platformdirs/__init__.py
platformdirs/__main__.py
platformdirs/android.py
platformdirs/api.py
platformdirs/macos.py
platformdirs/py.typed
platformdirs/unix.py
platformdirs/version.py
platformdirs/windows.py
platformdirs-4.3.5.dist-info/METADATA
platformdirs-4.3.5.dist-info/WHEEL
platformdirs-4.3.5.dist-info/licenses/LICENSE
platformdirs-4.3.5.dist-info/RECORD
